{
  "id": 1044,
  "name": "Aranjuez Cultural Landscape",
  "source_lang": "ja",
  "source_url": "https://ja.wikipedia.org/wiki/%E3%82%A2%E3%83%A9%E3%83%B3%E3%83%95%E3%82%A8%E3%82%B9%E3%81%AE%E6%96%87%E5%8C%96%E7%9A%84%E6%99%AF%E8%A6%B3",
  "retrieved": "2026-07-09",
  "text": "アランフエス（Aranjuez）は、スペイン・マドリード州南部に位置するムニシピオ（基礎自治体）。タホ川に沿って広がり、ハラマ川との合流点がある。首都マドリードから南に48km。\nスペイン王室の宮殿と庭園が有名で、世界遺産に登録されている。また、ホアキン・ロドリーゴの楽曲アランフエス協奏曲でもその名を知られる。\n\n\n== 歴史 ==\nアランフエスの地名はバスク語由来という説がある。言語学者のラファエル・ラペサはバスク語の「アランツァ」（サンザシ）という説を示しているが、「アラン」（谷または同音異義のプラム）かもしれない。アラビア語の「イブン・アランケジュ」（クルミの生える所）という説やラテン語の「アラ・ヨウィス」（ジュピター神殿）という説も唱えられている。7世紀の文献には「アラウス」や「アランス」という名前で現れ、「アランスエケ」などと呼ばれた後に、15世紀に「アランフエス」に落ち着いた。\n1085年にアルフォンソ6世がトレドを征服した後も、アランフエスはカスティーリャ王国とイスラム諸国の間で争奪が行われた。1178年に最終的に征服され、アランフエスはサンティアゴ騎士団に与えられた。15世紀末、カトリック両王によって王室の土地とされた。1561年、フェリペ2世の命により宮殿の建築が始まった。18世紀のフェルナンド6世によってアランフエスが生まれたが、当時に住んでいたのは宮廷関係者だけであった。\n1808年、宰相マヌエル・デ・ゴドイの支配に対してアランフエス暴動が発生した。これによってゴドイが失脚、カルロス4世が退位し、フェルナンド7世が即位するが、ナポレオンの介入によってジョゼフ・ボナパルトがスペイン王となった。\n1851年、スペインで2番目となる鉄道（イチゴ列車と呼ばれる）がマドリード＝アランフエス間に開通し、マドリードの近郊都市として産業が発展した。\n\n\n== 人口 ==\n\n\n== 政治 ==\n自治体首長はマドリード国民党（Partido Popular de la Comunidad de Madrid）のマリア・ホセーファ・マルティネス・デ・ラ・フエンテ（María José Martínez de la Fuente）で、自治体評議員はマドリード国民党：14、マドリード社会党（Partido Socialista de Madrid）：8、アランフエスのための独立市民グループ（Agrupación Ciudadana Independiente Para Aranjuez、ACIPA、ローカル政党）：2、統一左翼＝緑の党（Izquierda Unida-Los Verdes、IU-LV、統一左翼の州支部政党連合マドリード統一左翼と緑の党＝緑グループとヒラ・マドリード＝緑の党の連合体）：1となっている（2011年5月22日の自治体選挙結果、得票順）。\n\n\n=== 司法行政 ===\nアランフエスはアランフエス司法管轄区に属し、同管轄区の中心自治体である。\n\n\n== 王宮と庭園 ==\n\nアランフエスの王宮は、16世紀にフェリペ2世の命で建設が始められたものである。設計は、エル・エスコリアルと同じくフアン・バウティスタ・デ・トレドとフアン・デ・エレラによる。18世紀のフェルナンド6世の治世に完成し、カルロス3世によって拡張された。\n王宮からタホ川に沿って広がる庭園（es）は、森や庭からなり、多くの泉や像で飾られている。王宮正面の「パルテレ庭園」、タホ川と人工の川に囲まれた「島の庭園」、タホ川に沿って延びる150haの「王子の庭園」などからなる。かつては王室の農業試験場でもあり、スペイン黄金時代に世界から集めた植物が栽培されていた。\n\n\n=== 世界遺産 ===\n2001年、王宮と庭園を含む風景は「アランフエスの文化的景観」としてユネスコの世界遺産（文化遺産）に登録された。自然と人工物からなる景観が何百年も維持され発展してきたことが評価された。この世界遺産は世界遺産登録基準のうち、以下の条件を満たし、登録された（以下の基準は世界遺産センター公表の登録基準からの翻訳、引用である）。\n\n(2) ある期間を通じてまたはある文化圏において、建築、技術、記念碑的芸術、都市計画、景観デザインの発展に関し、人類の価値の重要な交流を示すもの。\n(4) 人類の歴史上重要な時代を例証する建築様式、建築物群、技術の集積または景観の優れた例。\n\n\n=== ギャラリー ===\n\n\n== 交通 ==\n\n鉄道では、マドリードのアトーチャ駅から近郊路線C-3で45分。朝と夕方は10-20分おき、昼と夜は30分おきに電車がある。4月から10月まで、マドリードから観光用に19世紀の蒸気機関車「イチゴ列車」（es:Tren de la Fresa）が走っている。\nマドリードとカディスを結ぶ高速道路A-4が通っている。\n\n\n== 姉妹都市 ==\n エシハ、スペイン\n ル・ペック、フランス\n\n\n== 脚注 ==\n\n\n== 参考文献 ==\nICOMOSによる報告書（PDF、英語、フランス語）\n\n\n== 関連項目 ==\nアランフエス協奏曲 - ホアキン・ロドリーゴによるギター協奏曲。\n\n\n== 外部リンク ==\n\n公式ウェブサイト（スペイン語）\nイチゴ列車 - 鉄道博物館（スペイン語）\nアランフエス スペイン政府観光局（日本語）"
}