{
  "id": 1442,
  "name": "シルクロード:長安-天山回廊の交易路網",
  "source_lang": "ja",
  "source_url": "https://ja.wikipedia.org/wiki/%E3%82%B7%E3%83%AB%E3%82%AF%E3%83%AD%E3%83%BC%E3%83%89_(%E4%B8%96%E7%95%8C%E9%81%BA%E7%94%A3)",
  "retrieved": "2026-07-02",
  "text": "この記事では、世界遺産としてのシルクロードについて扱う。\nユーラシア大陸の東西交流史において重要な役割を果たしたシルクロードは、その歴史的意義からUNESCOの世界遺産リストへの登録が目指されている。第1号として中華人民共和国（中国）、カザフスタン、キルギスの関連遺跡など計33件が2014年に「シルクロード:長安-天山回廊の交易路網」の名で登録され、第2号としてタジキスタン、ウズベキスタン、トルクメニスタンの関連遺跡など計34件が2023年に「シルクロード:ザラフシャン＝カラクム回廊」の名で登録された。\n\n\n== 登録経緯 ==\n\nシルクロードという名称は、ドイツの地理学者フェルディナント・フォン・リヒトホーフェンがその著書『中国』第1巻（1877年）で、東西交流における絹の重要性を指摘するとともに、中国からインドへと至る中央アジアの交易路を「絹の道」（ドイツ語で「ザイデンシュトラーセン」）と命名したことによって誕生した。この概念を拡張したのがアルベルト・ヘルマンで、著書『中国とシリア間の古代シルクロード』（1910年）はその題名が示すように、「絹の道」をシリアへと拡張するものであった。その後も調査・研究の進展に伴い概念が拡張され、現在では北緯50度線付近のステップを横断する「ステップ路」、北緯40度線付近のオアシス群を辿る「オアシス路」、更には南方の海を利用する「南海路」の3つに大別されるようになっている。\nこうしたシルクロード群について、1988年にUNESCOは「UNESCOシルクロード総合研究」というシンポジウムのシリーズを開始した。これはユーラシア大陸を横断した文化的伝播についての理解と文化財保護を促進するためのものであった。\n\n2002年11月17日から20日には西安市で「UNESCO国際学術シンポジウム」が開催された。この席上、UNESCOとともに主催者として名を連ねていた平山郁夫は、中国当局とともに、長安（現・西安）からローマに至るシルクロード全区間の世界遺産登録の構想を示した。この構想は、シンポジウムで採択された西安宣言とともに、UNESCO事務局長松浦晃一郎、国際連合事務総長コフィー・アナンに提出された提案書に盛り込まれた。\n2006年8月に、UNESCOと中国の国家文物局は、新疆ウイグル自治区のトルファン市で開催された会議（トルファン会議）を共同で後援した。この会議では、シルクロード関連遺産の世界遺産リスト登録への申請の協力関係について話し合われた。この会議において、中国と中央アジア5か国（カザフスタン、キルギス、タジキスタン、ウズベキスタン、トルクメニスタン）は、2010年の共同推薦に向けて合意した。さらに、同年10月のサマルカンド会議でコンセプトペーパーの作成準備が提案され、翌年4月のドゥシャンベ会議で最初のコンセプトペーパーが採択された。このコンセプトペーパーは西安よりも西の地域を対象としていたが、シルクロードは日本などへの文化的伝播も視野に入りうる。そこで、山内和也、前田耕作ら日本の専門家がコンセプトペーパーの修正を提言し、同年10月の西安会議以降、日本も正式に参加していくこととなった。\n2008年2月5日にはイランがホラーサーン地方のシルクロード関連遺産を世界遺産の暫定リストに記載し、翌月の28日には中国が48件の関連遺産を暫定リストに記載し、登録に向けた動きが具体化した。\n2009年には「連続性のある文化遺産としてのシルクロード」第1回調整委員会が西安市にて開催された。これに続き、2010年には1月20日にインドが12件の構成資産を暫定リストに記載し、2月19日にはキルギスが6件の構成資産を、ウズベキスタンが18件の構成資産をそれぞれ暫定リストに記載し、3月1日にはトルクメニスタンがシルクロードの11区間の29遺跡を暫定リストに記載した。\n2011年の第2回調整委員会（アシガバード）では、前出の中国と中央アジア5か国に加え、アフガニスタン、ネパール、インド、イラン、大韓民国、日本が参加したが、この席では最優先すべき推薦は中国と中央アジア5か国によることが確認された。\n2011年末にUNESCOは、その広大さを理由に、登録申請を「回廊」(corridors)  ごとに分割してはどうかと提案した。 同年12月に中国、カザフスタン、キルギスは、中原から天山山脈を横断する回廊を共同推薦することに合意した。こうした実際の推薦に向けた動きの中、シルクロードの世界遺産登録と中央アジアへの経済的影響力の強化を結びつける中国は、推薦準備に遅れが見られたウズベキスタンとタジキスタンを排除したとされる。そのタジキスタンとウズベキスタンは別の回廊での推薦準備を行うこととなった。\n2012年3月5日にはカザフスタンが暫定リストへの記載を行い、2013年1月に中国、カザフスタン、キルギスは長安-天山回廊を正式に推薦した。同じ月にタジキスタンとウズベキスタンもパンジケント-サマルカンド-ポイケント回廊の正式推薦に漕ぎつけた。それらは翌年の6月に開催された第38回世界遺産委員会で審議され、前者は正式登録を果たしたが、後者の登録は見送られた。正式登録を果たしたカザフスタンの代表は、その世界遺産委員会審議の場で、資金援助や人材育成に尽力してきた日本の名を挙げ、その協力への感謝を表明した。\n長安-天山回廊に関する世界遺産委員会の決議では、いくつかの付帯条項が添えられ、保護・管理面の強化のほか、さらなる拡大登録の努力とそのためのシルクロード研究の深化などが挙げられた。実際、日本の専門家からは、中央アジア諸国の拡大登録の支援とともに、日本の文化財の拡大登録を目指すべきという声も聞かれた。\nタジキスタン、ウズベキスタンの関連遺跡は、トルクメニスタンも加えた3国で、シルクロード:ザラフシャン＝カラクム回廊として、2023年の第45回世界遺産委員会にて正式登録を果たした。\n以下では、第一号として登録された長安-天山回廊と、今後登録を目指している暫定リスト記載物件群について個別に説明する。\n\n\n== シルクロード:長安-天山回廊の交易路網 ==\n\nシルクロード:長安-天山回廊の交易路網（シルクロード:ちょうあん-てんざんかいろうのこうえきろもう）は、2014年の第38回世界遺産委員会でUNESCOの世界遺産リストに登録された文化遺産の一つであり、ユーラシア大陸の東西交流史において重要な位置を占めたシルクロードの遺跡群のうち、中華人民共和国（中国）、カザフスタン、キルギスの3か国33資産で構成されている。\n\n\n=== 推薦と登録 ===\n前述の通り、中国がシルクロードを暫定リストに記載したのは2008年3月28日のことだった。その時の名称は「前漢時代から清代までのシルクロードの中国部分、すなわち河南省・陝西省・甘粛省・青海省・寧夏回族自治区・新疆ウイグル自治区の陸路、および浙江省寧波市・福建省泉州市の海路」(Chinese Section of the Silk Road : Land routes in Henan Province, Shaanxi Province, Gansu Province, "
}