{
  "id": 1517,
  "name": "ピリッポイ",
  "source_lang": "ja",
  "source_url": "https://ja.wikipedia.org/wiki/%E3%83%94%E3%83%AA%E3%83%83%E3%83%9D%E3%82%A4",
  "retrieved": "2026-07-12",
  "text": "ピリッポイ（古代ギリシア語:  Φἱλιπποι/ Philippoi）は、東マケドニア（現ギリシア領）にあった古代都市。紀元前356年にピリッポス2世によって創建され、14世紀にオスマン帝国に征服された後、廃れた。現在の都市フィリッポイ（2011年にカヴァラと合併）は、この都市の遺構近くに位置している。日本語聖書の訳語慣行ではピリピ、フィリピとも。新約聖書の一書『フィリピの信徒への手紙』の宛先としても知られる。その都市遺跡と古戦場跡は2016年に世界遺産リストに加えられた。\n\n\n== 創建 ==\nピリッポイは古代マケドニア王ピリッポス2世によって、タソス人の植民都市クレニデス（泉の意）があった場所に創建された。エーゲ海の最北端に近いピリッポイは、オルベロス山（現在のレカニ山）の麓に位置し、カヴァラの12km北西にあり、現在の平野部の北端に位置する。この平野部は当時一面の沼地であって、この沼によってピリッポイは南のパンガイオン丘陵から隔てられていた。ピリッポス2世の意図は、この都市をもって、付近の金鉱の開発を促進し、また軍事防衛の拠点とすることにあった。ピリッポスは海岸沿いの二都市、アンピポリスとネアポリスを結ぶ街道を防衛する要地であった。のちにこの街道は古代ローマにより再興されて、エグナティア街道となる。ピリッポス2世以降、歴代の王は、ピリッポイに自治権を認めた。またピリッポス2世は、南の沼地を干拓させた。\n紀元前167年アンティゴノス朝が滅び、ローマ領となったマケドニアは四つに分割された。ピリッポイはアンピポリスを首府とする東マケドニアに編入された。この時期の遺構はあまり残っていない。\n\n\n== ローマ時代 ==\n\nローマの内乱時代の末期、ユリウス・カエサルの死後、オクタウィアヌスとマルクス・アントニウスは連合して、カエサルの暗殺者マルクス・ユニウス・ブルートゥスとガイウス・カッシウス・ロンギヌスをピリッポイの西に破った（フィリッピの戦い、紀元前42年）。戦後、勝者二人は何人かの退役兵をピリッポイに入植させ、戦勝を記念して市をコローニア・ウィクトリクス・ピリッペンシウム（フィリッペンシウム）（Colonia Victrix Philippensium）と改称した。紀元前30年にオクタウィアヌスはさらに市の再建を進め、イタリアから多くの退役兵をピリッポスに入植させた。市は彼の氏族名ユリアにちなんでコローニア・ユリア・ピリッピネンシス（フィリッピネンシス）（Colonia Iulia Philippensis）と改称され、さらに紀元前27年、オクタウィアヌスが元老院からアウグストゥスの称号を贈られた後、コローニア・アウグスタ・ユリア・ピリッピネンシス（フィリッピネンシス）（Colonia Augusta Iulia Philippensis）と改称された。\n2回目の改名後、そしておそらく第一回目の改名の後にも、ピリッポイの土地は四角上に区画割りされた上で、入植者に分配された。ピリッポイにはマケドニア時代の市城が残り、市の設計は部分的にのみ変更された。以前からあったギリシア風のアゴラ（広場）の東側に、ローマ風のフォルム（広場）が追加された。ピリッポイはさながら小型のローマといった趣を呈した。ローマ法が適用され、ローマから直接任命された二人の軍人（duumviri）が市を治めた。\n付近の金鉱山ゆえに、ピリッポイの経済上の重要性はエグナティア街道沿いで際立っていた。この頃の遺構からは、ピリッポイの富がしのばれる。比較的小規模な都市に、大きなモニュメントが数多く存在しており、主要な道路の両側に拡がるテラスからなるフォルムが、クラウディウス帝からアントニウス・ピウス帝の治世の間に、数次にわたって造営された。また古い円形劇場は拡張され、ローマ風の競技会が行われた。ラテン語の碑文が多く出土し、この時期の市の繁華が伺われる。\n紀元後49年か50年頃、使徒パウロは幻に導かれてピリッポイを訪れた（『使徒行伝』16:9-10）。パウロには、シラス、テモテ、おそらくはルカであるとされる使徒行伝の筆者が同行しており、パウロはこの街でキリスト教伝道を行った。ピリッポイはパウロが初めて訪れたヨーロッパの都市であり (『使徒行伝』16:12-40) 、パウロは、市の西を流れる川で、紫布を商うリュディアという女性に洗礼を授けた。パウロが占いを行う少女から悪霊を追い出したことで、市では暴動が起き、パウロとシラスは逮捕され、鞭打たれて投獄された (『使徒行伝』16:16-24)。その晩、地震が起きて牢屋の扉が開いた。牢番はこれをみて囚人が逃げ出したものと思い自殺を図ったが、パウロはこれを止めた。牢番とその家族はキリストを信じた (『使徒行伝』16:25-40)。彼らは新約聖書が伝えるヨーロッパでの初めてのキリスト教改宗者である。また使徒行伝によれば、ピリッポイのユダヤ人コミュニティはささやかなものでシナゴーグは存在していなかった (『使徒行伝』16:13)。そのためにユダヤ人たちは、川辺に集まって礼拝を行っていた。\nパウロはその後2回、56年と57年にピリッポイを訪れている。『フィリピの信徒への手紙』は61年から62年に書かれたと推測されており、パウロがピリッポイの信徒たちに直接影響を与えていたことが窺える。ピリッポイにおけるその後のキリスト教の展開は、スミュルナ主教ポリュカリポスがピリッポイの信徒に宛てた160年頃の書簡、およびいくつかの墓碑によって知られている。\n\n\n== 初期キリスト教時代 ==\n\nピリッポイで知られている最初の聖堂は、小さな建物で、元来は祈りのための小さな家であったと思われる。敷石のモザイク碑文から「パウロ聖堂（バシリカ）」と呼ばれるこの建物は、343年のセルディカ教会会議に出席した主教ポルピュリオスの書簡から、その頃に建てられたと推定される。\nこの土地においてパウロがキリスト教徒共同体を創建した証拠は、考古学上も文献上も存在しないが、ピリッポイは5世紀と6世紀にこの地方のキリスト教の中心となり、それはパウロの宣教に由来すると考えられた。他の都市と同様、ピリッポイには多くの新しい教会建築が建てられた。4世紀中ごろから6世紀にかけて、7つの異なる聖堂が建てられ、そのうちの幾つかは美しさと大きさにおいてテサロニケやコンスタンティノポリスの著名な聖堂に比肩するものとなった。パウロ聖堂のあった場所には、5世紀の終わりに大聖堂が建てられた。大聖堂は八角形で、コンスタンティノポリスの聖堂にも劣らなかった。\nこの時代に、バルカン人の脅威に備え、市の城塞が再建された。473年に、ピリッポイは東ゴート人に包囲された。市は陥落をまぬかれたが、周辺の村落が焼き討ちにあった。\n\n\n== ビザンティンおよびオスマン時代 ==\n\n6世紀の終わり、スラヴ人の侵略によりマケドニアの農業経営は崩壊し、またおそらくは547年の疫病大流行（en:Plague of Justinian）の影響もあって、ピリッポイはかなり弱体化していた。619年頃、地震によって都市は完全に破壊され、その打撃から二度と復興することはなかった。7世紀にもある程度"
}