{
  "id": 1606,
  "name": "Migratory Bird Sanctuaries along the Coast of Yellow Sea-Bohai Gulf of China (Phase I)",
  "source_lang": "en",
  "source_url": "https://en.wikipedia.org/wiki/Yancheng%20Coastal%20Wetlands",
  "retrieved": "2026-07-11",
  "text": "The Yancheng Coastal Wetlands is the largest coastal wetlands nature reserve in China. It is situated close to Yancheng, Jiangsu province, China.\n\n\n== Location ==\nThe reserve is located in the east part of Yancheng, Jiangsu Province and in the coastal area of SheYang, DaFeng, XiangShui, BinHai and DongTai counties. The coast is 582 kilometers long and the area covers 453,000 hectares. The reserve faces the south of Yellow Sea and backs by the north flatland of JiangSu Province.\nIt is named after the Dongbei and Liao Rivers is connected to the Songnen Plain through the Yellow River Valley; a small plain lies north of Dongting Lake in the west.\n\n\n== Species ==\nIt has more than 600 kinds of natural vegetation, 379 kinds of birds, 281 kinds of shellfish, 590 kinds of insects, 47 kinds of mammal and another 490 kinds of plants. In 1992, The Nation Rare Birds Nature Reserve was built in Yancheng Wetlands. The  Yancheng Nature Reserve is especially known for the red-crowned cranes. Every winter, hundreds of red-crowned crane migrate to wintering sites in the Yancheng Nature Reserve. There are about 3,000,000 birds fly through Yancheng. Among these birds, more than 500,000 birds overwinter in Yancheng Nature Reserve.\n\n\n== See also ==\nGeography of China\n\n\n== References ==\n\"Yancheng Coastal Wetlands\". Archived from the original on 2002-08-28.\nhttp://www.wwt.org.uk/text/516/yangcheng_dafeng_national_nature_reserves.html Archived 2008-11-20 at the Wayback Machine\nhttp://www.chinaculture.org/gb/en_aboutchina/2003-09/24/content_21419.htm\n\n\n== External links ==\nWetland Biodiversity Conservation and Sustainable Use in China Project - Yancheng Coastal Wetlands"
}