{
  "id": 308,
  "name": "ヨセミテ国立公園",
  "source_lang": "ja",
  "source_url": "https://ja.wikipedia.org/wiki/%E3%83%A8%E3%82%BB%E3%83%9F%E3%83%86%E5%9B%BD%E7%AB%8B%E5%85%AC%E5%9C%92",
  "retrieved": "2026-06-29",
  "text": "ヨセミテ国立公園（ヨセミテこくりつこうえん、Yosemite National Park [joʊˈsɛmɨti] ）は、アメリカ合衆国カリフォルニア州中央部のマリポサ郡及びトゥオルミ郡にある、自然保護を目的とした国立公園である。そこに住んでいたネイティブアメリカンの部族の呼称から名づけられた。\n1864年、州立公園に指定。1890年、国立公園に指定。1984年、ユネスコの世界遺産（自然遺産）に登録された。\n\n\n== 概要 ==\n公園の面積は3081平方キロメートル（東京都の約1.4倍）で、シエラネバダ山脈の西山麓に広がっている。ここには年間430万人以上（2017年）が訪れるが、そのほとんどが集まるのは公園全体の1%にも満たないヨセミテ渓谷（約18平方キロメートル）である。\n1984年に世界遺産に登録され、そそり立つ白い花崗岩の絶壁、そこを流れ落ちる多くの巨大な滝、谷や木々の間を流れる澄んだ大小の川、ジャイアントセコイアの巨木の林、生物学的な多様性が世界的に知られることとなった。公園全体の約95%は原生地域に指定されている。ヨセミテは、第1号の国立公園であるイエローストーン国立公園より指定は遅いが、ガレン・クラーク (Galen Clark) やジョン・ミューア (John Muir) といった先達の貢献により、アメリカの国立公園の発展の上では中心的な役割を果たした。\nヨセミテ国立公園は、シエラネバダ山脈の中で最大規模の、最もまとまった動植物の生息地であり、生物の多様性を育んでいる。公園は高度600mから4,000mの地域を含み、大きく分けて次の5つの植生帯から成っている。低木・オーク林帯 (chaparral/oak woodland)、低地・低山植生帯 (lower montane)、高地・低山植生帯 (upper montane)、亜高山帯 (subalpine)、および高山帯 (alpine) である。カリフォルニア州には7,000種の植物が生えているが、そのうちの50%がシエラネバダ山脈にあり、20%以上がヨセミテ公園内に見られる。160種以上の稀少植物の植生地域があり、その形成にはヨセミテのたぐいまれな地質学的形成過程と、特異な土壌が寄与している。また、アメリカグマや、アライグマなどの哺乳類が約100種類、鳥類が200種類以上生息している。セコイアの大木でも有名である。\nヨセミテを地質学的に見ると、花崗岩が大部分を覆い、それより古い岩石が残りの部分を占めている。およそ1000万年前にシエラネバダ山塊が隆起し、その後傾斜したことにより、西側には緩やかな高原が、東側には急峻な山肌が生まれた。この隆起に伴って、川の流れは急になり、流れにえぐられて、深く、狭い渓谷・峡谷が形成された。次いで、約100万年前に、降り積もった雪と氷が氷河となって高山の草原帯を覆い、谷に沿って流れ下り始めた。氷期初めには、ヨセミテ渓谷を埋め尽くした氷の厚さは約1200メートルに達したと考えられている。この氷河の流れに削られたことによって、U字谷が現れた。\n\n\n== 地理 ==\n\n\n=== 位置 ===\n\nヨセミテ国立公園は、カリフォルニア州シエラネバダ山脈の中央部にある。サンフランシスコからは車で約3時間半、ロサンゼルスからは約6時間、サンバーナーディーノからは約7時間である。周りには原生地域が広がり、南東にアンセル・アダムス自然保護区域、北東にフーバー自然保護区域、北にエミグラント自然保護区域がある。\n公園の面積は3,080km2で、およそロードアイランド州の面積に匹敵する。何千もの湖沼、2600kmの渓流、1,300kmのハイキング・トレイル、560kmの道路がある。自然・景勝河川として連邦政府に指定されたマーセド川とトゥオルミ川は、ヨセミテの域内を流れた後、シエラネバダ山脈の麓を西へ通ってカリフォルニアセントラルヴァレーへ流れ込む。年間の来場者は430万人を超え、ほとんどの人がヨセミテ渓谷の約18km2のエリアに集まる。\n\n\n=== 岩石 ===\nヨセミテの地形のほとんどは、シエラネバダ・バソリス（バソリスとは、地中深くで従来の岩石に貫入した火成岩の大きな塊をいう）の花崗岩からできている。その他5%（主に公園の東端、ダナ山近く）は、変成作用を受けた火山岩と堆積岩でできている。これらの岩石は「ルーフ・ペンダント」と呼ばれるが、それは花崗岩の上に乗った屋根のような状態を示すからである。\n隆起によって形成された岩石の節理（割れ目）に浸食作用が働くことによって、現在の渓谷、ドームなどの地形が生み出された。節理が生じる間隔は、花崗岩及び花崗閃緑岩に含まれる二酸化ケイ素（シリカ）の量による。二酸化ケイ素の含有量が多いほど、岩石の強度は増し、節理の間隔は広くなる。\nワシントン・コラムやロスト・アローのような岩柱は、節理が交差して生まれる。こうした岩石の節理に対する浸食作用の中でも、この数百万年の間で最も大きかったのが、アルプス型の氷河によるものであった。それまで河川によってV字型に削られていた谷は、氷河によってU字型の渓谷になった（ヨセミテ渓谷やヘッチ・ヘッチー渓谷がそれに当たる）。また、節理どうしの間隔が広い花崗岩に、剥離作用（深成岩の結晶が表面で膨張する傾向によって生じる）が加わることによって、現在のハーフドームやノースドームといったドーム地形、ロイヤル・アーチのようなアーチ地形が生まれた。\n\n\n=== 有名なポイント ===\n\nヨセミテ渓谷は、国立公園全体の1%にすぎないが、ほとんどの観光客が訪れ、滞在する場所である。エル・キャピタンは、花崗岩の絶壁であり、様々なクライミング・ルートがあること、1年を通じて登れることから、世界中でも人気の高いロッククライミングのスポットである。花崗岩ドームのセンチネルドーム、ハーフドームはそれぞれ渓谷の底から約1160メートル、1470メートルの高さがある。\n\nヨセミテには、トゥオルミ・メドウズ、ダナ・メドウズ、クラーク・レンジ、カセドラル・レンジ、クナ・クレストといった美しいエリアが数多くある。シエラネバダの尾根とパシフィック・クレスト・トレイルがヨセミテを縦走し、ダナ山、ギブズ山のような赤色変成岩の峰、コネス山のような花崗岩の峰がある。ライエル山は公園の中での最高峰である。\n古代のセコイアデンドロン（ジャイアントセコイア）の林が、マリポサ・グローブ（200本）、トゥオルミ・グローブ（25本）、マーセド・グローブ（20本）の3か所ある。セコイアデンドロンは、他のどんな木よりも巨大に成長する植物で、体積でも寿命でも際立っている。最後の氷期が始まる前には、今よりずっと広範囲に生えていた。\n\n\n=== 水系 ===\n\nトゥオルミ川とマーセド川の水系は、公園内のシエラネバダ山脈の尾根に沿って流れ出し、およそ910mから1,200mの深さの渓谷を作り出している。トゥオルミ川は公園の北半分、約1800km2の範囲の水を集め、マーセド川は公園の南側の峰々、カセドラル・レンジやクラーク・レンジに源流を発し、約1320km2の範囲から水を集める。\n氷河、洪水、河川の流れなど、水の作用は、公"
}