{
  "id": 421,
  "name": "トンガリロ国立公園",
  "source_lang": "ja",
  "source_url": "https://ja.wikipedia.org/wiki/%E3%83%88%E3%83%B3%E3%82%AC%E3%83%AA%E3%83%AD%E5%9B%BD%E7%AB%8B%E5%85%AC%E5%9C%92",
  "retrieved": "2026-07-01",
  "text": "トンガリロ国立公園(トンガリロこくりつこうえん、英語：Tongariro National Park)は、ニュージーランドの北島にある、山岳地帯を保護する目的で設定された国立公園である。1894年、ニュージーランド初の国立公園となった。ユネスコの世界遺産（複合遺産）に登録されている。\n\n\n== 概要 ==\n\n最高峰ルアペフ山(2,797 m)や、富士山に似た稜線を持つナウルホエ山(2,291 m)などの活火山や死火山が広がる795km2の広さを持つ。トンガリロ山(1,967 m)には、エメラルド色に輝く火山湖がある。\nルアペフ山、ナウルホエ山、トンガリロ山の三峰は、マオリ族古来の聖地であった。1887年、当時のマオリ族の首長であったホロヌク・テ・ヘウヘウ・トゥキノは、ニュージーランド政府に2,630ヘクタールの土地を寄付したことが、トンガリロ国立公園の成立の始まりである。その結果、1894年、トンガリロ国立公園法が可決され、ニュージーランド最古の国立公園が成立した。1907年には、国立公園の面積は、25,213ヘクタールに拡大された。国立公園の拡大は、1922年、1953年、1962年、1975年と継続され、現在に至っている。\nまた、この国立公園の山域はマオリ族の信仰対象でもあった。マオリ族の文化との結びつきが考慮され、文化と自然の複合遺産として世界遺産に登録された。\n\n\n== 地理 ==\n\n\n=== 位置 ===\n\nタウポ湖から程近く、オークランドから南に約330キロメートル、ウェリントンから北320キロメートルのところに位置する。ワンガヌイ川は、トンガリロ国立公園内に源流を持ち、西に流れ、ワンガヌイ国立公園へと流れていく。\n公園のほとんどが、マナワツ・ワンガヌイ地方に所属しているが、公園の北東部は、ワイカト地方に所属する。\nトンガリロ国立公園の境界は、東が国道1号、北が国道46号（ラロトイア・ロード）、北西が国道47号、西が国道4号、南を国道49号が形成する。国道4号と国道49号に並行する形で、北島を縦断し、オークランドとウェリントンを結ぶ鉄道幹線である北島本線が走り、国道4号と47号の交差点の近くには、国立公園駅がある。\nトンガリロ国立公園内には、ニュージーランドの国道で最短の距離である国道48号がある。国道47号より分岐し、トンガリロ国立公園の観光拠点であるファカパパスキー場に至る。\n\n\n=== 気候 ===\nニュージーランドの大部分が温帯（西岸海洋性気候）に属しており、トンガリロ国立公園も、例外ではない。標高の高いトンガリロ国立公園は、タスマン海から東に抜ける偏西風にさらされており、雨雲も多くはタスマン海からもたらされる。極端な乾季・雨季の区別はなく、1年中、降水の可能性がある気候である。ファカパパスキー場では、年間2,200ミリの降水を記録し、公園南部のオハクニでは年間1,250ミリを記録する。\n気温は、標高が高いこともあり、1日の日較差が大きい。ファカパパスキー場では、1年中、霜が降りることもありうる。年間の平均基本は、13℃。最高気温は25℃、最低気温はマイナス10℃になる。\n標高1,500m以上では、冬になると雪が降る。降雪は、標高1,500m以下でも起こりうる。トンガリロ国立公園内に降る雪は、ニュージーランド屈指のスキー・リゾートたらしめている。おおよそ、降雪は、早くて3月から遅くても11月までは降ることとなる。時々、夏（南半球のため、12月から2月）であっても、降雪する。ナウルホエ山及びトンガリロ山の噴火口内及び、ルアペフ山頂上には、万年雪として、雪は残る。\n\n\n== 世界遺産 ==\n\n\n=== 東半球における環太平洋火山帯最南端の場所（自然遺産） ===\n\nトンガリロ国立公園は、東半球における環太平洋火山帯の最南端に位置づけられる。トンガリロ国立公園を起点に北東方向に181年に大噴火を起こしたタウポ湖、1886年に大噴火を起こしたタラウェラ山、ベイ・オブ・プレンティ沖合いのホワイト島までの火山群を総称した「タウポ火山帯」が伸びる。\nトンガリロ国立公園内の3つの火山は、おおむね若い。トンガリロ国立公園内で最初に噴火したのは、トンガリロ山で約26万年前のことである。ナウルホエ山が最初に噴火したのは、約2,500年前のことであると考えられており、伝統的に、ナウルホエ山の噴火周期は9年周期と考えられている。もっとも、ナウルホエ山の最後の噴火は、1975年のことである。\nトンガリロ国立公園の最高峰であるルアペフ山の最初の噴火は、トンガリロ山とほぼ同じ25万年前と考えられている。ルアペフ山の頂上にほぼ近いところに、酸性の火山湖が存在する。この火山湖は、深さ100メートル、直径600メートルある。水温の変化にしたがって、温度が上がるにつれ、緑や青から灰色へと変化する。ルアペフ山が噴火する際には、火山湖の水がラハール_(火山泥流)と化す。ラハールの発生は、ルアペフ山の噴火予知には欠くことができない。\n1945年の噴火活動で形成された火山湖が、1953年のクリスマス・イブに決壊し、ニュージーランドにおける最大の鉄道事故であるタンギワイ鉄道事故の原因ともなったし、それ以後も、1995年から96年、2007年にも噴火している。\n1990年に世界遺産（自然遺産）に登録されるにあたり、ほかの火山との比較検討がされた。比較対象となったのは、スペインのティマンファヤ国立公園、タンザニアのキリマンジャロ、エクアドルのサンガイ山、アラスカ州のカトマイ山及びハワイ州の火山群である。その中においても、トンガリロ国立公園は、マオリ族との文化的紐帯が強いと言う点で、ほかの火山群には見られない特徴を有していたと国際自然保護連合（IUCN）は結論付けた。\nトンガリロ国立公園が世界遺産（自然遺産）として、登録されたのは、以下の3点の特徴を有していた点にある。第1点が、火山活動が活発であり、「理想的な自然研究室」であったこと、第2点が、ルアペフ山の火山湖が頻繁な噴火によって形成されると同時に、氷河湖としての特徴をも有していたこと、第3点が186年のタウポ湖噴火を初めとして、1800年間の噴火の歴史の状態が良好であった点である。\n1990年時点での適合基準は以下の通りである。\n\n自然遺産7、8\n\n\n=== マオリ族の聖地として（文化遺産） ===\nニュージーランド（マオリ語でアオテアロア、Aotearoa）にポリネシア人が定住したのは、およそ1300年ごろとされる。マオリ族の文化は、豊かな口承伝承によって残されており、その口承伝承は、人々とニュージーランドの織り成す風景との間の関係が中心的な役割を果たしてきた。\n彼らのカヌー艦隊の中で、最も重要なカヌーがアラワ号であり、アラワ号船員の子孫と伝えられるマオリ族の内のンガティ部族である。19世紀、南オーストラリア州総督、2度のニュージーランド総督、ケープ植民地総督を歴任したジョージ・グレイは、以下のマオリ族の伝承を記録している。\nガティ部族の祖先で、アラワ号の航海者にして司祭であったナトロイランギは、探検者でもあった。ベイ・オブ・プレンティに上陸した彼は、北東内陸部へと"
}