{
  "id": 704,
  "name": "三孔",
  "source_lang": "ja",
  "source_url": "https://ja.wikipedia.org/wiki/%E4%B8%89%E5%AD%94",
  "retrieved": "2026-07-06",
  "text": "三孔（さんこう）とは:\n\n曲阜にある孔子ゆかりの史跡、孔府、孔廟、孔林、のこと。（本稿で説明）\n孔（あな）が三つあること。三孔ピトー管など。\n\n三孔（さんこう、拼音: sānkǒng、サンコン）とは、山東省、曲阜市にある孔子ゆかりの建造物、すなわち孔廟、孔府、孔林のことである。1994年以降、ユネスコの世界遺産（文化遺産）に登録された。中国の5A級観光地（2007年認定）でもある。\n\n\n== 概要 ==\n孔廟孔子の神霊を祭る霊所。孔子の死後、その教えを保護した皇帝達によって手が加えられ、紫禁城、岱廟と並ぶ中国三大宮廷建築の一つとされ、中国の代表的建築物といわれる。\n孔府孔子の直系の子孫が代々住み、且つオフィスとしていたところ。\n孔林200haを越える面積を持つ、孔子及びその子孫の墓。\n\n\n== 登録基準 ==\nこの世界遺産は世界遺産登録基準のうち、以下の条件を満たし、登録された（以下の基準は世界遺産センター公表の登録基準からの翻訳、引用である）。\n\n(1) 人類の創造的才能を表現する傑作。\n(4) 人類の歴史上重要な時代を例証する建築様式、建築物群、技術の集積または景観の優れた例。\n(6) 顕著で普遍的な意義を有する出来事、現存する伝統、思想、信仰または芸術的、文学的作品と直接にまたは明白に関連するもの（この基準は他の基準と組み合わせて用いるのが望ましいと世界遺産委員会は考えている）。\n\n\n== 脚注 ==\n\n\n== 関連項目 ==\n孔廟\n孔府\n孔林\n\n\n== 外部リンク ==\n\n孔廟\n孔子誕生の地"
}